__init__.py
smexperiments/__init__.py
smexperiments/_base_types.py
smexperiments/_boto_functions.py
smexperiments/_environment.py
smexperiments/_utils.py
smexperiments/api_types.py
smexperiments/experiment.py
smexperiments/metrics.py
smexperiments/search_expression.py
smexperiments/tracker.py
smexperiments/training_job.py
smexperiments/trial.py
smexperiments/trial_component.py
sagemaker_experiments-0.1.43.dist-info/LICENSE
sagemaker_experiments-0.1.43.dist-info/METADATA
sagemaker_experiments-0.1.43.dist-info/NOTICE
sagemaker_experiments-0.1.43.dist-info/WHEEL
sagemaker_experiments-0.1.43.dist-info/top_level.txt
sagemaker_experiments-0.1.43.dist-info/RECORD
