Metadata-Version: 2.1
Name: sagemaker-experiments
Version: 0.1.43
Summary: Open source library for Experiment Tracking in SageMaker Jobs and Notebooks
Home-page: https://github.com/aws/sagemaker-experiment-tracking/
Author: Amazon Web Services
License: Apache License 2.0
Keywords: ML Amazon AWS AI Tensorflow MXNet
Platform: UNKNOWN
Classifier: Development Status :: 5 - Production/Stable
Classifier: Intended Audience :: Developers
Classifier: Natural Language :: English
Classifier: License :: OSI Approved :: Apache Software License
Classifier: Programming Language :: Python
Classifier: Programming Language :: Python :: 3.7
Classifier: Programming Language :: Python :: 3.8
Classifier: Programming Language :: Python :: 3.9
Classifier: Programming Language :: Python :: 3.10
Classifier: Programming Language :: Python :: 3.11
License-File: LICENSE
License-File: NOTICE
Requires-Dist: boto3 (>=1.16.27)
Provides-Extra: test
Requires-Dist: tox (==3.13.1) ; extra == 'test'
Requires-Dist: flake8 ; extra == 'test'
Requires-Dist: pytest ; extra == 'test'
Requires-Dist: pytest-cov ; extra == 'test'
Requires-Dist: pytest-coverage ; extra == 'test'
Requires-Dist: pytest-rerunfailures ; extra == 'test'
Requires-Dist: pytest-xdist ; extra == 'test'
Requires-Dist: docker ; extra == 'test'
Requires-Dist: pandas ; extra == 'test'
Requires-Dist: scikit-learn ; extra == 'test'
